<?xml version="1.0" ?>
<!DOCTYPE PubmedArticleSet PUBLIC "-//NLM//DTD PubMedArticle, 1st January 2025//EN" "https://dtd.nlm.nih.gov/ncbi/pubmed/out/pubmed_250101.dtd">
<PubmedArticleSet>
<PubmedArticle><MedlineCitation Status="In-Process" Owner="NLM"><PMID Version="1">41758665</PMID><DateRevised><Year>2026</Year><Month>02</Month><Day>27</Day></DateRevised><Article PubModel="Print-Electronic"><Journal><ISSN IssnType="Electronic">1091-6490</ISSN><JournalIssue CitedMedium="Internet"><Volume>123</Volume><Issue>9</Issue><PubDate><Year>2026</Year><Month>Mar</Month><Day>03</Day></PubDate></JournalIssue><Title>Proceedings of the National Academy of Sciences of the United States of America</Title><ISOAbbreviation>Proc Natl Acad Sci U S A</ISOAbbreviation></Journal><ArticleTitle>Microbial metabolite oxindole curbs acute lung injury by suppressing CXCL13.</ArticleTitle><Pagination><StartPage>e2519332123</StartPage><MedlinePgn>e2519332123</MedlinePgn></Pagination><ELocationID EIdType="doi" ValidYN="Y">10.1073/pnas.2519332123</ELocationID><Abstract><AbstractText>The gut-lung axis is involved in acute lung injury (ALI) and its fatal sequela, acute respiratory distress syndrome (ARDS), yet the molecular mechanisms governing this crosstalk remain poorly defined. Untargeted metabolomics of plasma revealed significant dysregulation of tryptophan metabolism in ARDS patients compared to healthy controls. Murine dietary interventions demonstrated that high tryptophan intake alleviated ALI severity, whereas deficiency exacerbated injury, with protection being gut microbiota dependent. 16S ribosomal RNA (16S rRNA) gene sequencing revealed marked depletion of a functionally central bacterium <i>Lactobacillus johnsonii</i> (<i>L. johnsonii</i>) during ALI. Supplementation with <i>L. johnsonii</i> or its encapsulated form attenuated ALI, but this required dietary tryptophan sufficiency. Mechanistically, <i>L. johnsonii</i> converts tryptophan into oxindole, which enters pulmonary macrophages, promotes the aryl hydrocarbon receptor-RelA binding, and thereby suppresses RelA-mediated transcriptional activation of C-X-C motif chemokine 13 (CXCL13). Both genetic ablation and pharmacological inhibition of CXCL13 ameliorated ALI symptoms. Importantly, oxindole and CXCL13 levels correlated with ARDS severity in patients, suggesting their clinical relevance. Collectively, these findings define a protective microbiota-dependent gut-lung axis in ALI/ARDS that is mediated by dietary tryptophan-derived oxindole, which acts at least partially through CXCL13 suppression to underscore targetable diet-microbe-metabolite therapeutic paradigms.</AbstractText></Abstract><AuthorList CompleteYN="Y"><Author ValidYN="Y" EqualContrib="Y"><LastName>Tang</LastName><ForeName>Shixin</ForeName><Initials>S</Initials><Identifier Source="ORCID">0009-0005-0695-0968</Identifier><AffiliationInfo><Affiliation>Department of Health Laboratory Technology, School of Public Health, Chongqing Medical University, Chongqing 400016, China.</Affiliation></AffiliationInfo></Author><Author ValidYN="Y" EqualContrib="Y"><LastName>Zhang</LastName><ForeName>Jun</ForeName><Initials>J</Initials><AffiliationInfo><Affiliation>Department of Respiratory and Critical Care Medicine, The First Affiliated Hospital of Chongqing Medical University, Key Laboratory of Clinical Laboratory Diagnostics (Ministry of Education), College of Laboratory Medicine, Chongqing Medical University, Chongqing 400016, China.</Affiliation></AffiliationInfo></Author><Author ValidYN="Y" EqualContrib="Y"><LastName>He</LastName><ForeName>Zhenghai</ForeName><Initials>Z</Initials><Identifier Source="ORCID">0009-0002-1785-4603</Identifier><AffiliationInfo><Affiliation>Department of Pharmacy, The First Affiliated Hospital of Chongqing Medical University, Chongqing 400016, China.</Affiliation></AffiliationInfo></Author><Author ValidYN="Y" EqualContrib="Y"><LastName>Liu</LastName><ForeName>Gang</ForeName><Initials>G</Initials><AffiliationInfo><Affiliation>Department of Emergency, The University-Town Hospital of Chongqing Medical University, Chongqing 401331, China.</Affiliation></AffiliationInfo></Author><Author ValidYN="Y" EqualContrib="Y"><LastName>Nie</LastName><ForeName>Shenyou</ForeName><Initials>S</Initials><AffiliationInfo><Affiliation>Basic Medicine Research and Innovation Center for Novel Target and Therapeutic Intervention (Ministry of Education), Department of Urology of the Second Affiliated Hospital, College of Pharmacy, Chongqing Medical University, Chongqing 400016, China.</Affiliation></AffiliationInfo></Author><Author ValidYN="Y"><LastName>Shi</LastName><ForeName>Xingyang</ForeName><Initials>X</Initials><AffiliationInfo><Affiliation>Department of Respiratory and Critical Care Medicine, The First Affiliated Hospital of Chongqing Medical University, Key Laboratory of Clinical Laboratory Diagnostics (Ministry of Education), College of Laboratory Medicine, Chongqing Medical University, Chongqing 400016, China.</Affiliation></AffiliationInfo></Author><Author ValidYN="Y"><LastName>Zhang</LastName><ForeName>Kun</ForeName><Initials>K</Initials><AffiliationInfo><Affiliation>Department of Respiratory and Critical Care Medicine, The First Affiliated Hospital of Chongqing Medical University, Key Laboratory of Clinical Laboratory Diagnostics (Ministry of Education), College of Laboratory Medicine, Chongqing Medical University, Chongqing 400016, China.</Affiliation></AffiliationInfo></Author><Author ValidYN="Y"><LastName>Pi</LastName><ForeName>Dandan</ForeName><Initials>D</Initials><Identifier Source="ORCID">0000-0003-2585-4494</Identifier><AffiliationInfo><Affiliation>Department of Intensive Care Unit, Children's Hospital of Chongqing Medical University, Chongqing 400014, China.</Affiliation></AffiliationInfo></Author><Author ValidYN="Y"><LastName>Gui</LastName><ForeName>Xiao</ForeName><Initials>X</Initials><AffiliationInfo><Affiliation>Department of Emergency, The University-Town Hospital of Chongqing Medical University, Chongqing 401331, China.</Affiliation></AffiliationInfo></Author><Author ValidYN="Y"><LastName>He</LastName><ForeName>Yi</ForeName><Initials>Y</Initials><AffiliationInfo><Affiliation>Basic Medicine Research and Innovation Center for Novel Target and Therapeutic Intervention (Ministry of Education), Department of Urology of the Second Affiliated Hospital, College of Pharmacy, Chongqing Medical University, Chongqing 400016, China.</Affiliation></AffiliationInfo></Author><Author ValidYN="Y"><LastName>Zhao</LastName><ForeName>Shuang</ForeName><Initials>S</Initials><AffiliationInfo><Affiliation>Basic Medicine Research and Innovation Center for Novel Target and Therapeutic Intervention (Ministry of Education), Department of Urology of the Second Affiliated Hospital, College of Pharmacy, Chongqing Medical University, Chongqing 400016, China.</Affiliation></AffiliationInfo></Author><Author ValidYN="Y"><LastName>Liu</LastName><ForeName>Zhihui</ForeName><Initials>Z</Initials><AffiliationInfo><Affiliation>Department of Respiratory and Critical Care Medicine, The First Affiliated Hospital of Chongqing Medical University, Key Laboratory of Clinical Laboratory Diagnostics (Ministry of Education), College of Laboratory Medicine, Chongqing Medical University, Chongqing 400016, China.</Affiliation></AffiliationInfo></Author><Author ValidYN="Y"><LastName>Mao</LastName><ForeName>Lejiao</ForeName><Initials>L</Initials><AffiliationInfo><Affiliation>Department of Respiratory and Critical Care Medicine, The First Affiliated Hospital of Chongqing Medical University, Key Laboratory of Clinical Laboratory Diagnostics (Ministry of Education), College of Laboratory Medicine, Chongqing Medical University, Chongqing 400016, China.</Affiliation></AffiliationInfo></Author><Author ValidYN="Y"><LastName>Jiang</LastName><ForeName>Yu</ForeName><Initials>Y</Initials><AffiliationInfo><Affiliation>Department of Respiratory Medicine, The University-Town Hospital of Chongqing Medical University, Chongqing 401331, China.</Affiliation></AffiliationInfo></Author><Author ValidYN="Y"><LastName>Wu</LastName><ForeName>Mingjun</ForeName><Initials>M</Initials><AffiliationInfo><Affiliation>Innovation Centre of Chongqing Medical University, Chongqing 400016, China.</Affiliation></AffiliationInfo></Author><Author ValidYN="Y"><LastName>Cao</LastName><ForeName>Ju</ForeName><Initials>J</Initials><Identifier Source="ORCID">0000-0002-4855-6986</Identifier><AffiliationInfo><Affiliation>Department of Laboratory Medicine, The First Affiliated Hospital of Chongqing Medical University, Chongqing 400016, China.</Affiliation></AffiliationInfo></Author><Author ValidYN="Y"><LastName>Qiu</LastName><ForeName>Jingfu</ForeName><Initials>J</Initials><AffiliationInfo><Affiliation>Department of Health Laboratory Technology, School of Public Health, Chongqing Medical University, Chongqing 400016, China.</Affiliation></AffiliationInfo></Author><Author ValidYN="Y"><LastName>Chen</LastName><ForeName>Chengzhi</ForeName><Initials>C</Initials><Identifier Source="ORCID">0000-0002-1087-4911</Identifier><AffiliationInfo><Affiliation>Department of Occupational and Environmental Health, School of Public Health, Chongqing Medical University, Chongqing 400016, China.</Affiliation></AffiliationInfo></Author><Author ValidYN="Y"><LastName>Zou</LastName><ForeName>Zhen</ForeName><Initials>Z</Initials><Identifier Source="ORCID">0000-0002-1651-591X</Identifier><AffiliationInfo><Affiliation>Department of Respiratory and Critical Care Medicine, The First Affiliated Hospital of Chongqing Medical University, Key Laboratory of Clinical Laboratory Diagnostics (Ministry of Education), College of Laboratory Medicine, Chongqing Medical University, Chongqing 400016, China.</Affiliation></AffiliationInfo><AffiliationInfo><Affiliation>Western Institute of Digital-Intelligent Medicine, Chongqing 401329, China.</Affiliation></AffiliationInfo></Author></AuthorList><Language>eng</Language><GrantList CompleteYN="Y"><Grant><GrantID>32371177</GrantID><Agency>MOST | National Natural Science Foundation of China (NSFC)</Agency><Country/></Grant><Grant><GrantID>CSTB2022NSCQ-LZX0017</GrantID><Agency>Natural Science Foundation Project of Chongqing</Agency><Country/></Grant><Grant><GrantID>BJRC202419</GrantID><Agency>Chongqing Medical University 2024 Graduate Top Talent Cultivation Program</Agency><Country/></Grant></GrantList><PublicationTypeList><PublicationType UI="D016428">Journal Article</PublicationType></PublicationTypeList><ArticleDate DateType="Electronic"><Year>2026</Year><Month>02</Month><Day>27</Day></ArticleDate></Article><MedlineJournalInfo><Country>United States</Country><MedlineTA>Proc Natl Acad Sci U S A</MedlineTA><NlmUniqueID>7505876</NlmUniqueID><ISSNLinking>0027-8424</ISSNLinking></MedlineJournalInfo><CitationSubset>IM</CitationSubset><KeywordList Owner="NOTNLM"><Keyword MajorTopicYN="N">CXCL13</Keyword><Keyword MajorTopicYN="N">Lactobacillus johnsonii</Keyword><Keyword MajorTopicYN="N">acute lung injury</Keyword><Keyword MajorTopicYN="N">acute respiratory distress syndrome</Keyword><Keyword MajorTopicYN="N">oxindole</Keyword></KeywordList><CoiStatement>Competing interests statement:We have two authorized Chinese invention patents based on the achievements of this research (Z.L. 202211409265.8 and Z.L. 202310526774.7); another Chinese invention patent is still under examination (202410632322.1). The other authors declare no conflicts of interest.</CoiStatement></MedlineCitation><PubmedData><History><PubMedPubDate PubStatus="medline"><Year>2026</Year><Month>2</Month><Day>27</Day><Hour>19</Hour><Minute>31</Minute></PubMedPubDate><PubMedPubDate PubStatus="pubmed"><Year>2026</Year><Month>2</Month><Day>27</Day><Hour>19</Hour><Minute>31</Minute></PubMedPubDate><PubMedPubDate PubStatus="entrez"><Year>2026</Year><Month>2</Month><Day>27</Day><Hour>12</Hour><Minute>43</Minute></PubMedPubDate></History><PublicationStatus>ppublish</PublicationStatus><ArticleIdList><ArticleId IdType="pubmed">41758665</ArticleId><ArticleId IdType="doi">10.1073/pnas.2519332123</ArticleId></ArticleIdList></PubmedData></PubmedArticle></PubmedArticleSet>